coopmovers/IAgentStatusStruct.py
coopmovers/IAgentTracker.py
coopmovers/__init__.py
coopmovers/movers.py
coopmovers/segment.py
coopmovers/segmentfollower.py
coopmovers/segmentfollowerhub.py
coopmovers/traffic/__init__.py
coopmovers/traffic/intersection.py
coopmovers/traffic/intersectionHub.py
coopmovers/traffic/trafficDirector.py
coopmovers-0.3.dist-info/LICENSE
coopmovers-0.3.dist-info/METADATA
coopmovers-0.3.dist-info/WHEEL
coopmovers-0.3.dist-info/top_level.txt
coopmovers-0.3.dist-info/RECORD
